{"stat.walkOneCm":94353,"stat.leaveGame":3,"stat.mineBlock.minecraft.vine":4,"stat.mineBlock.minecraft.double_plant":21,"stat.jump":191,"stat.swimOneCm":8493,"stat.fallOneCm":3681,"stat.mineBlock.minecraft.wool":1,"stat.crouchOneCm":10,"achievement.mineWood":11,"stat.sprintOneCm":38509,"achievement.exploreAllBiomes":{"value":0,"progress":["Beach","Birch Forest","River","Forest","Plains"]},"stat.useItem.minecraft.sapling":1,"achievement.openInventory":11,"stat.mineBlock.minecraft.log2":8,"stat.damageTaken":60,"stat.mineBlock.minecraft.red_flower":3,"stat.mobKills":1,"stat.mineBlock.minecraft.log":8,"stat.flyOneCm":22667,"stat.mineBlock.minecraft.leaves":8,"stat.playOneMinute":14385,"stat.killEntity.Sheep":1,"stat.damageDealt":80,"stat.useItem.minecraft.wool":1,"stat.timeSinceDeath":14385,"stat.mineBlock.minecraft.dirt":11,"stat.mineBlock.minecraft.tallgrass":351,"stat.diveOneCm":3735}